{
    "version": 1.18,
    "waypoints": [
        {
            "x": 0.7068282245732163,
            "y": 4.390995865827678,
            "r": 120,
            "p": 52,
            "c": "S"
            "v": 1.8,
            "passthrough": 0
        },
        {
            "x": 4,
            "y": 1.460522216159027,
            "r": 180,
            "p": 20,
            "c": "g"
            "v": 1.8,
            "passthrough": 1
        },
        {
            "x": 8.284519366083364,
            "y": 0.760522216159027,
            "r": 180,
            "p": 20,
            "c": "G"
            "v": 1.8,
            "passthrough": 0
        },
        {
            "x": 4,
            "y": 1.460522216159027,
            "r": 180,
            "p": 20,
            "c": "g"
            "v": 1.8,
            "passthrough": 1
        },
        {
            "x": 1.6914308225480144,
            "y": 3.410056397917379,
            "r": 120,
            "p": 45,
            "c": "Sg"
            "v": 1.8,
            "passthrough": 0
        },
        {
            "x": 4,
            "y": 1.460522216159027,
            "r": 180,
            "p": 20,
            "c": "g"
            "v": 1.8,
            "passthrough": 1
        },
        {
            "x": 8.29917188634136,
            "y": 2.442444488326853,
            "r": 210,
            "p": 20,
            "c": "G"
            "v": 1.8,
            "passthrough": 0
        },
        {
            "x": 4,
            "y": 1.460522216159027,
            "r": 180,
            "p": 20,
            "c": "g"
            "v": 1.8,
            "passthrough": 1
        },
        {
            "x": 1.6914308225480144,
            "y": 3.410056397917379,
            "r": 120,
            "p": 45,
            "c": "sg"
            "v": 1.8,
            "passthrough": 0
        }
    ]
}
